pyflakes/__init__.py
pyflakes/__main__.py
pyflakes/api.py
pyflakes/checker.py
pyflakes/messages.py
pyflakes/reporter.py
pyflakes/scripts/__init__.py
pyflakes/scripts/pyflakes.py
pyflakes/test/__init__.py
pyflakes/test/harness.py
pyflakes/test/test_api.py
pyflakes/test/test_builtin.py
pyflakes/test/test_code_segment.py
pyflakes/test/test_dict.py
pyflakes/test/test_doctests.py
pyflakes/test/test_imports.py
pyflakes/test/test_is_literal.py
pyflakes/test/test_match.py
pyflakes/test/test_other.py
pyflakes/test/test_type_annotations.py
pyflakes/test/test_undefined_names.py
pyflakes-3.3.1.dist-info/LICENSE
pyflakes-3.3.1.dist-info/METADATA
pyflakes-3.3.1.dist-info/WHEEL
pyflakes-3.3.1.dist-info/entry_points.txt
pyflakes-3.3.1.dist-info/top_level.txt
pyflakes-3.3.1.dist-info/RECORD
