Metadata-Version: 2.1
Name: pyflakes
Version: 3.3.1
Summary: passive checker of Python programs
Home-page: https://github.com/PyCQA/pyflakes
Author: A lot of people
Author-email: code-quality@python.org
License: MIT
Classifier: Development Status :: 6 - Mature
Classifier: Environment :: Console
Classifier: Intended Audience :: Developers
Classifier: License :: OSI Approved :: MIT License
Classifier: Programming Language :: Python
Classifier: Programming Language :: Python :: 3
Classifier: Programming Language :: Python :: 3 :: Only
Classifier: Programming Language :: Python :: Implementation :: CPython
Classifier: Programming Language :: Python :: Implementation :: PyPy
Classifier: Topic :: Software Development
Classifier: Topic :: Utilities
Requires-Python: >=3.9
License-File: LICENSE
